README.md
setup.cfg
setup.py
pgtail/__init__.py
pgtail/cli.py
pgtail.egg-info/PKG-INFO
pgtail.egg-info/SOURCES.txt
pgtail.egg-info/dependency_links.txt
pgtail.egg-info/entry_points.txt
pgtail.egg-info/not-zip-safe
pgtail.egg-info/requires.txt
pgtail.egg-info/top_level.txt